{
  "id": "death-effects",
  "title": "Death Effects",
  "description": "A module for FoundryVTT to add JRPG-like death effects for your tokens!",
  "version": "#{VERSION}#",
  "library": "false",
  "compatibility": {
    "minimum": 13,
    "verified": 13,
    "maximum": 14
  },
  "authors": [
    {
      "name": "Unarekin",
      "url": "https://github.com/Unarekin",
      "discord": "unarekin"
    }
  ],
  "socket": true,
  "relationships": {
    "systems": [],
    "requires": []
  },
  "esmodules": ["module.js"],
  "scripts": [
    "vendor/pixi-filters.js",
    "greensock/dist/gsap.min.js",
    "greensock/dist/PixiPlugin.min.js",
    "vendor/animation-timeline.min.js"
  ],
  "styles": ["styles/module.css"],
  "languages": [
    {
      "lang": "en",
      "name": "English",
      "path": "languages/en.json"
    }
  ],
  "url": "#{URL}#",
  "manifest": "#{MANIFEST}#",
  "download": "#{DOWNLOAD}#",
  "license": "LICENSE",
  "readme": "README.md"
}
